{
  "quote": {
    "1010.SR": {
      "price": 26.78,
      "date": "2025-08-19"
    },
    "1020.SR": {
      "price": 12.47,
      "date": "2025-08-19"
    },
    "1030.SR": {
      "price": 13.81,
      "date": "2025-08-19"
    },
    "1050.SR": {
      "price": 16.8,
      "date": "2025-08-19"
    },
    "1060.SR": {
      "price": 32.02,
      "date": "2025-08-19"
    },
    "1080.SR": {
      "price": 21.74,
      "date": "2025-08-19"
    },
    "1111.SR": {
      "price": 170.3,
      "date": "2025-08-19"
    },
    "1120.SR": {
      "price": 95.45,
      "date": "2025-08-19"
    },
    "1140.SR": {
      "price": 26.44,
      "date": "2025-08-19"
    },
    "1150.SR": {
      "price": 25.52,
      "date": "2025-08-19"
    },
    "1180.SR": {
      "price": 35.88,
      "date": "2025-08-19"
    },
    "1182.SR": {
      "price": 12.76,
      "date": "2025-08-19"
    },
    "1183.SR": {
      "price": 22.27,
      "date": "2025-08-19"
    },
    "1201.SR": {
      "price": 7.52,
      "date": "2025-08-19"
    },
    "1202.SR": {
      "price": 27.72,
      "date": "2025-08-19"
    },
    "1210.SR": {
      "price": 27.14,
      "date": "2025-08-19"
    },
    "1211.SR": {
      "price": 52.85,
      "date": "2025-08-19"
    },
    "1212.SR": {
      "price": 149.7,
      "date": "2025-08-19"
    },
    "1213.SR": {
      "price": 102.5,
      "date": "2025-08-19"
    },
    "1214.SR": {
      "price": 28.32,
      "date": "2025-08-19"
    },
    "1301.SR": {
      "price": 23.52,
      "date": "2025-08-19"
    },
    "1302.SR": {
      "price": 58.75,
      "date": "2025-08-19"
    },
    "1303.SR": {
      "price": 9.32,
      "date": "2025-08-19"
    },
    "1304.SR": {
      "price": 33.88,
      "date": "2025-08-19"
    },
    "1320.SR": {
      "price": 51.5,
      "date": "2025-08-19"
    },
    "1321.SR": {
      "price": 110.0,
      "date": "2025-08-19"
    },
    "1322.SR": {
      "price": 63.25,
      "date": "2025-08-19"
    },
    "1323.SR": {
      "price": 30.22,
      "date": "2025-08-19"
    },
    "1810.SR": {
      "price": 25.76,
      "date": "2025-08-19"
    },
    "1820.SR": {
      "price": 2.31,
      "date": "2025-08-19"
    },
    "1830.SR": {
      "price": 149.7,
      "date": "2025-08-19"
    },
    "1831.SR": {
      "price": 4.82,
      "date": "2025-08-19"
    },
    "1832.SR": {
      "price": 2.94,
      "date": "2025-08-19"
    },
    "1833.SR": {
      "price": 132.9,
      "date": "2025-08-19"
    },
    "1834.SR": {
      "price": 5.9,
      "date": "2025-08-19"
    },
    "1835.SR": {
      "price": 57.4,
      "date": "2025-08-19"
    },
    "2001.SR": {
      "price": 10.11,
      "date": "2025-08-19"
    },
    "2010.SR": {
      "price": 58.95,
      "date": "2025-08-19"
    },
    "2020.SR": {
      "price": 120.1,
      "date": "2025-08-19"
    },
    "2030.SR": {
      "price": 58.0,
      "date": "2025-08-19"
    },
    "2040.SR": {
      "price": 30.34,
      "date": "2025-08-19"
    },
    "2050.SR": {
      "price": 24.09,
      "date": "2025-08-19"
    },
    "2060.SR": {
      "price": 10.14,
      "date": "2025-08-19"
    },
    "2070.SR": {
      "price": 26.9,
      "date": "2025-08-19"
    },
    "2080.SR": {
      "price": 74.65,
      "date": "2025-08-19"
    },
    "2081.SR": {
      "price": 127.9,
      "date": "2025-08-19"
    },
    "2082.SR": {
      "price": 228.0,
      "date": "2025-08-19"
    },
    "2083.SR": {
      "price": 40.0,
      "date": "2025-08-19"
    },
    "2084.SR": {
      "price": 25.5,
      "date": "2025-08-19"
    },
    "2090.SR": {
      "price": 19.8,
      "date": "2025-08-19"
    },
    "2100.SR": {
      "price": 26.7,
      "date": "2025-08-19"
    },
    "2110.SR": {
      "price": 151.3,
      "date": "2025-08-19"
    },
    "2120.SR": {
      "price": 24.01,
      "date": "2025-08-19"
    },
    "2130.SR": {
      "price": 33.18,
      "date": "2025-08-19"
    },
    "2140.SR": {
      "price": 12.42,
      "date": "2025-08-19"
    },
    "2150.SR": {
      "price": 41.18,
      "date": "2025-08-19"
    },
    "2160.SR": {
      "price": 20.28,
      "date": "2025-08-19"
    },
    "2170.SR": {
      "price": 36.64,
      "date": "2025-08-19"
    },
    "2180.SR": {
      "price": 32.48,
      "date": "2025-08-19"
    },
    "2190.SR": {
      "price": 35.36,
      "date": "2025-08-19"
    },
    "2200.SR": {
      "price": 5.88,
      "date": "2025-08-19"
    },
    "2210.SR": {
      "price": 27.06,
      "date": "2025-08-19"
    },
    "2220.SR": {
      "price": 17.07,
      "date": "2025-08-19"
    },
    "2222.SR": {
      "price": 24.1,
      "date": "2025-08-19"
    },
    "2223.SR": {
      "price": 86.2,
      "date": "2025-08-19"
    },
    "2230.SR": {
      "price": 7.13,
      "date": "2025-08-19"
    },
    "2240.SR": {
      "price": 38.8,
      "date": "2025-08-19"
    },
    "2250.SR": {
      "price": 18.07,
      "date": "2025-08-19"
    },
    "2270.SR": {
      "price": 275.0,
      "date": "2025-08-19"
    },
    "2280.SR": {
      "price": 46.72,
      "date": "2025-08-19"
    },
    "2281.SR": {
      "price": 83.65,
      "date": "2025-08-19"
    },
    "2282.SR": {
      "price": 51.85,
      "date": "2025-08-19"
    },
    "2283.SR": {
      "price": 51.55,
      "date": "2025-08-19"
    },
    "2284.SR": {
      "price": 31.38,
      "date": "2025-08-19"
    },
    "2285.SR": {
      "price": 42.28,
      "date": "2025-08-19"
    },
    "2286.SR": {
      "price": 4.12,
      "date": "2025-08-19"
    },
    "2287.SR": {
      "price": 40.9,
      "date": "2025-08-19"
    },
    "2290.SR": {
      "price": 31.98,
      "date": "2025-08-19"
    },
    "2300.SR": {
      "price": 56.65,
      "date": "2025-08-19"
    },
    "2310.SR": {
      "price": 18.76,
      "date": "2025-08-19"
    },
    "2320.SR": {
      "price": 58.95,
      "date": "2025-08-19"
    },
    "2330.SR": {
      "price": 32.86,
      "date": "2025-08-19"
    },
    "2340.SR": {
      "price": 12.48,
      "date": "2025-08-19"
    },
    "2350.SR": {
      "price": 4.99,
      "date": "2025-08-19"
    },
    "2360.SR": {
      "price": 27.52,
      "date": "2025-08-19"
    },
    "2370.SR": {
      "price": 33.08,
      "date": "2025-08-19"
    },
    "2380.SR": {
      "price": 7.54,
      "date": "2025-08-19"
    },
    "2381.SR": {
      "price": 74.95,
      "date": "2025-08-19"
    },
    "2382.SR": {
      "price": 14.81,
      "date": "2025-08-19"
    },
    "3002.SR": {
      "price": 8.11,
      "date": "2025-08-19"
    },
    "3003.SR": {
      "price": 16.31,
      "date": "2025-08-19"
    },
    "3004.SR": {
      "price": 7.83,
      "date": "2025-08-19"
    },
    "3005.SR": {
      "price": 15.05,
      "date": "2025-08-19"
    },
    "3007.SR": {
      "price": 25.5,
      "date": "2025-08-19"
    },
    "3008.SR": {
      "price": 2.16,
      "date": "2025-08-19"
    },
    "3010.SR": {
      "price": 21.66,
      "date": "2025-08-19"
    },
    "3020.SR": {
      "price": 33.66,
      "date": "2025-08-19"
    },
    "3030.SR": {
      "price": 38.92,
      "date": "2025-08-19"
    },
    "3040.SR": {
      "price": 43.34,
      "date": "2025-08-19"
    },
    "3050.SR": {
      "price": 26.2,
      "date": "2025-08-19"
    },
    "3060.SR": {
      "price": 16.17,
      "date": "2025-08-19"
    },
    "3080.SR": {
      "price": 26.88,
      "date": "2025-08-19"
    },
    "3090.SR": {
      "price": 10.68,
      "date": "2025-08-19"
    },
    "3091.SR": {
      "price": 6.68,
      "date": "2025-08-19"
    },
    "3092.SR": {
      "price": 29.94,
      "date": "2025-08-19"
    },
    "4001.SR": {
      "price": 7.62,
      "date": "2025-08-19"
    },
    "4002.SR": {
      "price": 74.55,
      "date": "2025-08-19"
    },
    "4003.SR": {
      "price": 88.05,
      "date": "2025-08-19"
    },
    "4004.SR": {
      "price": 130.7,
      "date": "2025-08-19"
    },
    "4005.SR": {
      "price": 177.9,
      "date": "2025-08-19"
    },
    "4006.SR": {
      "price": 16.22,
      "date": "2025-08-19"
    },
    "4007.SR": {
      "price": 34.08,
      "date": "2025-08-19"
    },
    "4008.SR": {
      "price": 29.22,
      "date": "2025-08-19"
    },
    "4009.SR": {
      "price": 57.95,
      "date": "2025-08-19"
    },
    "4011.SR": {
      "price": 12.99,
      "date": "2025-08-19"
    },
    "4012.SR": {
      "price": 3.68,
      "date": "2025-08-19"
    },
    "4013.SR": {
      "price": 254.6,
      "date": "2025-08-19"
    },
    "4014.SR": {
      "price": 36.4,
      "date": "2025-08-19"
    },
    "4015.SR": {
      "price": 161.5,
      "date": "2025-08-19"
    },
    "4016.SR": {
      "price": 126.6,
      "date": "2025-08-19"
    },
    "4017.SR": {
      "price": 39.36,
      "date": "2025-08-19"
    },
    "4018.SR": {
      "price": 169.8,
      "date": "2025-08-19"
    },
    "4020.SR": {
      "price": 18.24,
      "date": "2025-08-19"
    },
    "4030.SR": {
      "price": 22.14,
      "date": "2025-08-19"
    },
    "4031.SR": {
      "price": 46.16,
      "date": "2025-08-19"
    },
    "4040.SR": {
      "price": 13.73,
      "date": "2025-08-19"
    },
    "4050.SR": {
      "price": 52.7,
      "date": "2025-08-19"
    },
    "4051.SR": {
      "price": 5.6,
      "date": "2025-08-19"
    },
    "4061.SR": {
      "price": 15.51,
      "date": "2025-08-19"
    },
    "4070.SR": {
      "price": 15.84,
      "date": "2025-08-19"
    },
    "4071.SR": {
      "price": 88.75,
      "date": "2025-08-19"
    },
    "4072.SR": {
      "price": 29.9,
      "date": "2025-08-19"
    },
    "4080.SR": {
      "price": 10.31,
      "date": "2025-08-19"
    },
    "4081.SR": {
      "price": 12.47,
      "date": "2025-08-19"
    },
    "4082.SR": {
      "price": 11.28,
      "date": "2025-08-19"
    },
    "4083.SR": {
      "price": 155.2,
      "date": "2025-08-19"
    },
    "4084.SR": {
      "price": 26.7,
      "date": "2025-08-19"
    },
    "4090.SR": {
      "price": 36.58,
      "date": "2025-08-19"
    },
    "4100.SR": {
      "price": 77.1,
      "date": "2025-08-19"
    },
    "4110.SR": {
      "price": 2.27,
      "date": "2025-08-19"
    },
    "4130.SR": {
      "price": 3.12,
      "date": "2025-08-19"
    },
    "4140.SR": {
      "price": 2.11,
      "date": "2025-08-19"
    },
    "4141.SR": {
      "price": 27.16,
      "date": "2025-08-19"
    },
    "4142.SR": {
      "price": 137.1,
      "date": "2025-08-19"
    },
    "4143.SR": {
      "price": 41.4,
      "date": "2025-08-19"
    },
    "4144.SR": {
      "price": 58.75,
      "date": "2025-08-19"
    },
    "4150.SR": {
      "price": 32.82,
      "date": "2025-08-19"
    },
    "4160.SR": {
      "price": 39.58,
      "date": "2025-08-19"
    },
    "4161.SR": {
      "price": 5.63,
      "date": "2025-08-19"
    },
    "4162.SR": {
      "price": 59.6,
      "date": "2025-08-19"
    },
    "4163.SR": {
      "price": 67.05,
      "date": "2025-08-19"
    },
    "4164.SR": {
      "price": 115.0,
      "date": "2025-08-19"
    },
    "4165.SR": {
      "price": 124.2,
      "date": "2025-08-19"
    },
    "4170.SR": {
      "price": 0.98,
      "date": "2025-08-19"
    },
    "4180.SR": {
      "price": 3.16,
      "date": "2025-08-19"
    },
    "4190.SR": {
      "price": 12.62,
      "date": "2025-08-19"
    },
    "4191.SR": {
      "price": 40.32,
      "date": "2025-08-19"
    },
    "4192.SR": {
      "price": 6.98,
      "date": "2025-08-19"
    },
    "4193.SR": {
      "price": 24.22,
      "date": "2025-08-19"
    },
    "4210.SR": {
      "price": 171.4,
      "date": "2025-08-19"
    },
    "4220.SR": {
      "price": 12.62,
      "date": "2025-08-19"
    },
    "4230.SR": {
      "price": 43.76,
      "date": "2025-08-19"
    },
    "4240.SR": {
      "price": 22.75,
      "date": "2025-08-19"
    },
    "4250.SR": {
      "price": 18.71,
      "date": "2025-08-19"
    },
    "4260.SR": {
      "price": 70.3,
      "date": "2025-08-19"
    },
    "4261.SR": {
      "price": 62.75,
      "date": "2025-08-19"
    },
    "4262.SR": {
      "price": 60.05,
      "date": "2025-08-19"
    },
    "4263.SR": {
      "price": 169.3,
      "date": "2025-08-19"
    },
    "4264.SR": {
      "price": 80.0,
      "date": "2025-08-19"
    },
    "4270.SR": {
      "price": 12.23,
      "date": "2025-08-19"
    },
    "4280.SR": {
      "price": 7.76,
      "date": "2025-08-19"
    },
    "4290.SR": {
      "price": 22.69,
      "date": "2025-08-19"
    },
    "4291.SR": {
      "price": 168.0,
      "date": "2025-08-19"
    },
    "4292.SR": {
      "price": 64.95,
      "date": "2025-08-19"
    },
    "4300.SR": {
      "price": 19.61,
      "date": "2025-08-19"
    },
    "4310.SR": {
      "price": 12.76,
      "date": "2025-08-19"
    },
    "4320.SR": {
      "price": 19.0,
      "date": "2025-08-19"
    },
    "4321.SR": {
      "price": 20.62,
      "date": "2025-08-19"
    },
    "4322.SR": {
      "price": 13.6,
      "date": "2025-08-19"
    },
    "4323.SR": {
      "price": 38.8,
      "date": "2025-08-19"
    },
    "4324.SR": {
      "price": 4.85,
      "date": "2025-08-19"
    },
    "4325.SR": {
      "price": 22.96,
      "date": "2025-08-19"
    },
    "4330.SR": {
      "price": 5.3,
      "date": "2025-08-19"
    },
    "4331.SR": {
      "price": 13.65,
      "date": "2025-08-19"
    },
    "4332.SR": {
      "price": 5.29,
      "date": "2025-08-19"
    },
    "4333.SR": {
      "price": 9.63,
      "date": "2025-08-19"
    },
    "4334.SR": {
      "price": 9.06,
      "date": "2025-08-19"
    },
    "4335.SR": {
      "price": 4.24,
      "date": "2025-08-19"
    },
    "4336.SR": {
      "price": 4.67,
      "date": "2025-08-19"
    },
    "4337.SR": {
      "price": 4.32,
      "date": "2025-08-19"
    },
    "4338.SR": {
      "price": 6.96,
      "date": "2025-08-19"
    },
    "4339.SR": {
      "price": 5.49,
      "date": "2025-08-19"
    },
    "4340.SR": {
      "price": 8.17,
      "date": "2025-08-19"
    },
    "4342.SR": {
      "price": 10.23,
      "date": "2025-08-19"
    },
    "4344.SR": {
      "price": 6.66,
      "date": "2025-08-19"
    },
    "4345.SR": {
      "price": 4.51,
      "date": "2025-08-19"
    },
    "4346.SR": {
      "price": 3.74,
      "date": "2025-08-19"
    },
    "4347.SR": {
      "price": 9.16,
      "date": "2025-08-19"
    },
    "4348.SR": {
      "price": 5.67,
      "date": "2025-08-19"
    },
    "4349.SR": {
      "price": 8.16,
      "date": "2025-08-19"
    },
    "4350.SR": {
      "price": 8.53,
      "date": "2025-08-19"
    },
    "5110.SR": {
      "price": 14.51,
      "date": "2025-08-19"
    },
    "6001.SR": {
      "price": 46.38,
      "date": "2025-08-19"
    },
    "6002.SR": {
      "price": 23.7,
      "date": "2025-08-19"
    },
    "6004.SR": {
      "price": 101.5,
      "date": "2025-08-19"
    },
    "6010.SR": {
      "price": 21.45,
      "date": "2025-08-19"
    },
    "6012.SR": {
      "price": 13.33,
      "date": "2025-08-19"
    },
    "6013.SR": {
      "price": 106.6,
      "date": "2025-08-19"
    },
    "6014.SR": {
      "price": 52.15,
      "date": "2025-08-19"
    },
    "6015.SR": {
      "price": 2.12,
      "date": "2025-08-19"
    },
    "6016.SR": {
      "price": 16.18,
      "date": "2025-08-19"
    },
    "6017.SR": {
      "price": 23.51,
      "date": "2025-08-19"
    },
    "6020.SR": {
      "price": 15.98,
      "date": "2025-08-19"
    },
    "6040.SR": {
      "price": 10.26,
      "date": "2025-08-19"
    },
    "6050.SR": {
      "price": 90.2,
      "date": "2025-08-19"
    },
    "6060.SR": {
      "price": 16.55,
      "date": "2025-08-19"
    },
    "6070.SR": {
      "price": 44.08,
      "date": "2025-08-19"
    },
    "6090.SR": {
      "price": 10.79,
      "date": "2025-08-19"
    },
    "7010.SR": {
      "price": 42.84,
      "date": "2025-08-19"
    },
    "7020.SR": {
      "price": 65.2,
      "date": "2025-08-19"
    },
    "7030.SR": {
      "price": 10.77,
      "date": "2025-08-19"
    },
    "7040.SR": {
      "price": 103.9,
      "date": "2025-08-19"
    },
    "7200.SR": {
      "price": 133.1,
      "date": "2025-08-19"
    },
    "7201.SR": {
      "price": 5.36,
      "date": "2025-08-19"
    },
    "7202.SR": {
      "price": 245.6,
      "date": "2025-08-19"
    },
    "7203.SR": {
      "price": 890.0,
      "date": "2025-08-19"
    },
    "7204.SR": {
      "price": 10.57,
      "date": "2025-08-19"
    },
    "8010.SR": {
      "price": 125.5,
      "date": "2025-08-19"
    },
    "8012.SR": {
      "price": 12.47,
      "date": "2025-08-19"
    },
    "8020.SR": {
      "price": 13.4,
      "date": "2025-08-19"
    },
    "8030.SR": {
      "price": 16.94,
      "date": "2025-08-19"
    },
    "8040.SR": {
      "price": 14.41,
      "date": "2025-08-19"
    },
    "8050.SR": {
      "price": 12.31,
      "date": "2025-08-19"
    },
    "8060.SR": {
      "price": 12.33,
      "date": "2025-08-19"
    },
    "8070.SR": {
      "price": 13.8,
      "date": "2025-08-19"
    },
    "8100.SR": {
      "price": 14.28,
      "date": "2025-08-19"
    },
    "8120.SR": {
      "price": 12.52,
      "date": "2025-08-19"
    },
    "8150.SR": {
      "price": 11.14,
      "date": "2025-08-19"
    },
    "8160.SR": {
      "price": 10.62,
      "date": "2025-08-19"
    },
    "8170.SR": {
      "price": 11.31,
      "date": "2025-08-19"
    },
    "8180.SR": {
      "price": 14.12,
      "date": "2025-08-19"
    },
    "8190.SR": {
      "price": 5.45,
      "date": "2025-08-19"
    },
    "8200.SR": {
      "price": 47.8,
      "date": "2025-08-19"
    },
    "8210.SR": {
      "price": 152.8,
      "date": "2025-08-19"
    },
    "8230.SR": {
      "price": 119.5,
      "date": "2025-08-19"
    },
    "8240.SR": {
      "price": 33.1,
      "date": "2025-08-19"
    },
    "8250.SR": {
      "price": 25.12,
      "date": "2025-08-19"
    },
    "8260.SR": {
      "price": 5.03,
      "date": "2025-08-19"
    },
    "8270.SR": {
      "price": 16.9,
      "date": "2025-08-19"
    },
    "8280.SR": {
      "price": 12.75,
      "date": "2025-08-19"
    },
    "8300.SR": {
      "price": 15.51,
      "date": "2025-08-19"
    },
    "8310.SR": {
      "price": 7.95,
      "date": "2025-08-19"
    },
    "8311.SR": {
      "price": 9.35,
      "date": "2025-08-19"
    },
    "8313.SR": {
      "price": 96.25,
      "date": "2025-08-19"
    }
  }
}